yaps/__init__.py
yaps/api/__init__.py
yaps/api/async_methods.py
yaps/api/packet.py
yaps/api/protocol.py
yaps/api/protocol_utils.py
yaps/api/sync_methods.py
yaps/client/__init__.py
yaps/client/async_base_connection.py
yaps/client/async_client.py
yaps/client/async_publish.py
yaps/client/async_subscribe.py
yaps/client/base_connection.py
yaps/client/client.py
yaps/client/publish.py
yaps/client/subscribe.py
yaps/scripts/__init__.py
yaps/scripts/test/__init__.py
yaps/scripts/test/__main__.py
yaps/server/__init__.py
yaps/server/publication.py
yaps/server/server.py
yaps/server/server_request.py
yaps/server/subscription.py
yaps/server/subscription_container.py
yaps/utils/__init__.py
yaps/utils/argparser.py
yaps/utils/config.py
yaps/utils/log.py
yaps/utils/log_user.py
yaps_lib-0.0.1.data/scripts/yaps-publish
yaps_lib-0.0.1.data/scripts/yaps-server
yaps_lib-0.0.1.data/scripts/yaps-subscribe
yaps_lib-0.0.1.dist-info/LICENSE
yaps_lib-0.0.1.dist-info/METADATA
yaps_lib-0.0.1.dist-info/WHEEL
yaps_lib-0.0.1.dist-info/top_level.txt
yaps_lib-0.0.1.dist-info/RECORD
