Metadata-Version: 2.1
Name: yaps-lib
Version: 0.0.1
Summary: A lightweight publish, subscribe library
Home-page: https://github.com/victorhook/yaps
Author: Victor Krook
Author-email: victorkrook96@gmail.com
License: UNKNOWN
Project-URL: Bug Tracker, https://github.com/victorhook/yaps/issues
Platform: UNKNOWN
Classifier: Programming Language :: Python :: 3
Classifier: License :: OSI Approved :: MIT License
Classifier: Operating System :: OS Independent
Requires-Python: >=3.8
